CHANGES.txt
LICENSE.txt
MANIFEST.in
README.txt
setup.py
examples/1MillionProcesses.py
examples/Commstime.py
examples/Commstime_Io.py
examples/Commstime_Multiprocesses.py
examples/Dining-Phil.py
examples/Fibonacci.py
examples/MCPi.py
examples/MCPiTrace.py
examples/MultipleTokenRing.py
examples/Sieve.py
examples/TerminationRacePoison.py
examples/TerminationRaceRetire.py
examples/TokenRing.py
examples/WebServer.py
examples/pycsp_import.py
examples/Mandelbrot/mandelbrot_ctypes.py
examples/Mandelbrot/mandelbrot_kernel.c
examples/Mandelbrot/mandelbrot_kernel.h
examples/Mandelbrot/pycsp_import.py
examples/problems/common.py
examples/problems/deadlock_doing_alternation_on_input_and_output_pre_0.6.1.py
examples/problems/greenlets_differentiate_between_deadlocking_and_all_executed_processes_pre_0.7.0.py
examples/problems/greenlets_exception_propagation_from_io_functions_pre_0.7.1.py
examples/problems/greenlets_unable_to_communicate_on_channels_from_main_namespace_pre_0.7.1.py
examples/problems/parallel_nesting_multiprocess_in_process.py
pycsp/__init__.py
pycsp.egg-info/PKG-INFO
pycsp.egg-info/SOURCES.txt
pycsp.egg-info/dependency_links.txt
pycsp.egg-info/top_level.txt
pycsp/common/__init__.py
pycsp/common/const.py
pycsp/common/plugNplay.py
pycsp/common/toolkit.py
pycsp/common/trace.py
pycsp/current/__init__.py
pycsp/greenlets/__init__.py
pycsp/greenlets/alternation.py
pycsp/greenlets/altselect.py
pycsp/greenlets/buffer.py
pycsp/greenlets/channel.py
pycsp/greenlets/channelend.py
pycsp/greenlets/compat.py
pycsp/greenlets/exceptions.py
pycsp/greenlets/guard.py
pycsp/greenlets/process.py
pycsp/greenlets/scheduling.py
pycsp/parallel/__init__.py
pycsp/parallel/alternation.py
pycsp/parallel/altselect.py
pycsp/parallel/channel.py
pycsp/parallel/compat.py
pycsp/parallel/configuration.py
pycsp/parallel/const.py
pycsp/parallel/dispatch.py
pycsp/parallel/exceptions.py
pycsp/parallel/guard.py
pycsp/parallel/header.py
pycsp/parallel/multiprocess.py
pycsp/parallel/ossocket.py
pycsp/parallel/process.py
pycsp/parallel/protocol.py
test/autotest.py
test/buffertest.py
test/check.py
test/commtest.py
